{
  "displayName": "Imperial",
  "ordinanceLabel": "Imperial Municipal Code · City-hosted PDFs · Imperial County Fire (contract)",
  "codePrefix": "IMC",
  "fireAgency": "Imperial County Fire Department (contract)",
  "climateZone": "15",
  "suggestedQuestions": [
    "What are the ADU rules in Imperial?",
    "How do I submit permit plans — what portal does Imperial use?",
    "Does my project need a construction waste management plan?",
    "What are the setback requirements for a fence in Imperial?",
    "Does Imperial have any local building code amendments?",
    "Who handles fire plan review for Imperial permits?"
  ]
}
